LICENSE.txt
MANIFEST.in
README.md
setup.cfg
setup.py
djangopubsub/__init__.py
djangopubsub/djangoPubSub.py
djangopubsub/handler.py
djangopubsub/lazy_pub_sub.py
djangopubsub.egg-info/PKG-INFO
djangopubsub.egg-info/SOURCES.txt
djangopubsub.egg-info/dependency_links.txt
djangopubsub.egg-info/not-zip-safe
djangopubsub.egg-info/requires.txt
djangopubsub.egg-info/top_level.txt
djangopubsub/management/__init__.py
djangopubsub/management/commands/__init__.py
djangopubsub/management/commands/runpubsubreceiver.py