Metadata-Version: 2.1
Name: djangopubsub
Version: 0.3.5
Summary: Base redis pubsub django wrapper
Home-page: https://gitlab.com/kas-factory/packages/django-pubsub
Author: Antonio @ KF
Author-email: antonio@kasfactory.net
License: COPYRIGHT
Platform: UNKNOWN
License-File: LICENSE.txt
